{
  "id": "MAP_FROST_CAVE",
  "name": "FrostCave",
  "layout": "LAYOUT_FROST_CAVE",
  "music": "MUS_ABANDONED_SHIP",
  "region_map_section": "MAPSEC_LITTLEROOT_TOWN",
  "requires_flash": false,
  "weather": "WEATHER_NONE",
  "map_type": "MAP_TYPE_NONE",
  "allow_cycling": true,
  "allow_escaping": false,
  "allow_running": true,
  "show_map_name": true,
  "battle_scene": "MAP_BATTLE_SCENE_NORMAL",
  "connections": 0,
  "object_events": [
    {
      "graphics_id": "OBJ_EVENT_GFX_YOUNGSTER",
      "x": 9,
      "y": 3,
      "elevation": 0,
      "movement_type": "MOVEMENT_TYPE_FACE_LEFT",
      "movement_range_x": 0,
      "movement_range_y": 0,
      "trainer_type": "0",
      "trainer_sight_or_berry_tree_id": "0",
      "script": "NULL",
      "flag": "FLAG_HIDE_MT_CHIMNEY_TEAM_MAGMA"
    },
    {
      "graphics_id": "OBJ_EVENT_GFX_YOUNGSTER",
      "x": 8,
      "y": 3,
      "elevation": 0,
      "movement_type": "MOVEMENT_TYPE_FACE_RIGHT",
      "movement_range_x": 0,
      "movement_range_y": 0,
      "trainer_type": "0",
      "trainer_sight_or_berry_tree_id": "0",
      "script": "NULL",
      "flag": "FLAG_HIDE_MT_CHIMNEY_TEAM_MAGMA"
    },
    {
      "graphics_id": "OBJ_EVENT_GFX_MANIAC",
      "x": 18,
      "y": 17,
      "elevation": 3,
      "movement_type": "MOVEMENT_TYPE_FACE_DOWN_AND_RIGHT",
      "movement_range_x": 0,
      "movement_range_y": 0,
      "trainer_type": "TRAINER_TYPE_NORMAL",
      "trainer_sight_or_berry_tree_id": "4",
      "script": "Route110_EventScript_Edwin",
      "flag": "0"
    },
    {
      "graphics_id": "OBJ_EVENT_GFX_MAN_3",
      "x": 18,
      "y": 21,
      "elevation": 3,
      "movement_type": "MOVEMENT_TYPE_FACE_UP_AND_LEFT",
      "movement_range_x": 1,
      "movement_range_y": 1,
      "trainer_type": "TRAINER_TYPE_NORMAL",
      "trainer_sight_or_berry_tree_id": "3",
      "script": "Route110_EventScript_Joseph",
      "flag": "0"
    },
    {
      "graphics_id": "OBJ_EVENT_GFX_HEX_MANIAC",
      "x": 26,
      "y": 12,
      "elevation": 3,
      "movement_type": "MOVEMENT_TYPE_FACE_RIGHT",
      "movement_range_x": 0,
      "movement_range_y": 0,
      "trainer_type": "TRAINER_TYPE_NORMAL",
      "trainer_sight_or_berry_tree_id": "4",
      "script": "Route110_EventScript_Edward",
      "flag": "0"
    },
    {
      "graphics_id": "OBJ_EVENT_GFX_WOMAN_3",
      "x": 31,
      "y": 12,
      "elevation": 3,
      "movement_type": "MOVEMENT_TYPE_FACE_LEFT",
      "movement_range_x": 1,
      "movement_range_y": 1,
      "trainer_type": "TRAINER_TYPE_NORMAL",
      "trainer_sight_or_berry_tree_id": "4",
      "script": "Route110_EventScript_Alyssa",
      "flag": "0"
    },
    {
      "graphics_id": "OBJ_EVENT_GFX_ITEM_BALL",
      "x": 7,
      "y": 20,
      "elevation": 3,
      "movement_type": "MOVEMENT_TYPE_LOOK_AROUND",
      "movement_range_x": 1,
      "movement_range_y": 1,
      "trainer_type": "TRAINER_TYPE_NONE",
      "trainer_sight_or_berry_tree_id": "0",
      "script": "ShoalCave_LowTideStairsRoom_EventScript_ItemIceHeal",
      "flag": "FLAG_ITEM_SHOAL_CAVE_STAIRS_ROOM_ICE_HEAL"
    },
    {
      "graphics_id": "OBJ_EVENT_GFX_ITEM_BALL",
      "x": 28,
      "y": 19,
      "elevation": 3,
      "movement_type": "MOVEMENT_TYPE_LOOK_AROUND",
      "movement_range_x": 1,
      "movement_range_y": 1,
      "trainer_type": "TRAINER_TYPE_NONE",
      "trainer_sight_or_berry_tree_id": "0",
      "script": "ShoalCave_LowTideIceRoom_EventScript_ItemTM07",
      "flag": "FLAG_ITEM_SHOAL_CAVE_ICE_ROOM_TM07"
    }
  ],
  "warp_events": [
    {
      "x": 3,
      "y": 18,
      "elevation": 0,
      "dest_map": "MAP_ERDBERG",
      "dest_warp_id": "0"
    },
    {
      "x": 2,
      "y": 18,
      "elevation": 0,
      "dest_map": "MAP_ERDBERG",
      "dest_warp_id": "0"
    },
    {
      "x": 23,
      "y": 8,
      "elevation": 0,
      "dest_map": "MAP_FROST_CAVE_UP1",
      "dest_warp_id": "0"
    },
    {
      "x": 11,
      "y": 3,
      "elevation": 0,
      "dest_map": "MAP_FROST_CAVE_UP1",
      "dest_warp_id": "1"
    },
    {
      "x": 35,
      "y": 19,
      "elevation": 0,
      "dest_map": "MAP_ROUTE1111",
      "dest_warp_id": "0"
    },
    {
      "x": 36,
      "y": 19,
      "elevation": 0,
      "dest_map": "MAP_ROUTE1111",
      "dest_warp_id": "0"
    },
    {
      "x": 14,
      "y": 10,
      "elevation": 0,
      "dest_map": "MAP_FROST_CAVE_UP1",
      "dest_warp_id": "6"
    },
    {
      "x": 29,
      "y": 12,
      "elevation": 0,
      "dest_map": "MAP_FROST_CAVE_UP1",
      "dest_warp_id": "3"
    },
    {
      "x": 23,
      "y": 4,
      "elevation": 0,
      "dest_map": "MAP_FROST_CAVE_UP1",
      "dest_warp_id": "5"
    },
    {
      "x": 15,
      "y": 2,
      "elevation": 0,
      "dest_map": "MAP_FROST_CAVE_UP1",
      "dest_warp_id": "7"
    },
    {
      "x": 37,
      "y": 7,
      "elevation": 0,
      "dest_map": "MAP_FROST_CAVE_UP1",
      "dest_warp_id": "4"
    },
    {
      "x": 29,
      "y": 17,
      "elevation": 0,
      "dest_map": "MAP_FROST_CAVE_UP1",
      "dest_warp_id": "2"
    },
    {
      "x": 4,
      "y": 2,
      "elevation": 0,
      "dest_map": "MAP_FROST_CAVE_UP2",
      "dest_warp_id": "0"
    }
  ],
  "coord_events": [

  ],
  "bg_events": [

  ]
}
